pg_user_auth/__init__.py
pg_user_auth/auth.py
user_auth/__init__.py
user_auth/auth.py
pg_user_auth-0.0.3.dist-info/LICENSE
pg_user_auth-0.0.3.dist-info/METADATA
pg_user_auth-0.0.3.dist-info/WHEEL
pg_user_auth-0.0.3.dist-info/top_level.txt
pg_user_auth-0.0.3.dist-info/RECORD
