Metadata-Version: 2.1
Name: pg-user-auth
Version: 0.0.3
Summary: user authentications
Home-page: 
Author: Sandakin Gunadasa
Author-email: sandakinh@gmail.com
License: UNKNOWN
Platform: UNKNOWN
Classifier: Programming Language :: Python :: 3
Classifier: License :: OSI Approved :: MIT License
Classifier: Operating System :: OS Independent
